{
  "canisters": {
    "token": {
      "type": "motoko",
      "main": "src/dfx/token.mo"
    },
    "staking": {
      "type": "motoko",
      "main": "src/staking/StakingCanister.mo"
    },
    "tmu_dao": {
      "type": "motoko",
      "main": "src/tmu_dao/main.mo"
    },
    "treasury": {
      "type": "motoko",
      "main": "src/treasury/TreasuryCanister.mo"
    }
  },
  "defaults": {
    "build": {
      "packtool": ""
    }
  },
  "networks": {
    "local": {
      "bind": "127.0.0.1:4943",
      "type": "ephemeral"
    }
  }
}